fhirpack/__init__.py
fhirpack/auth.py
fhirpack/base.py
fhirpack/base_test.py
fhirpack/cli.py
fhirpack/cli_test.py
fhirpack/config.py
fhirpack/config_test.py
fhirpack/conftest.py
fhirpack/constants.py
fhirpack/exceptions.py
fhirpack/pack.py
fhirpack/utils.py
fhirpack/utils_test.py
fhirpack/custom/__init__.py
fhirpack/custom/base.py
fhirpack/custom/utils.py
fhirpack/custom/extraction/__init__.py
fhirpack/custom/extraction/base.py
fhirpack/custom/extraction/sample.py
fhirpack/custom/load/__init__.py
fhirpack/custom/load/base.py
fhirpack/custom/load/sample.py
fhirpack/custom/transformation/__init__.py
fhirpack/custom/transformation/base.py
fhirpack/custom/transformation/sample.py
fhirpack/data/numpydoc.template
fhirpack/data/profiles.list
fhirpack/data/resourceTextElementMapping.json
fhirpack/data/resources.list
fhirpack/data/supported.list
fhirpack/data/config/hapi.fhir.org.env
fhirpack/data/config/test.fhir.org.env
fhirpack/data/logs/README.md
fhirpack/extraction/__init__.py
fhirpack/extraction/base.py
fhirpack/extraction/base_test.py
fhirpack/extraction/condition.py
fhirpack/extraction/condition_test.py
fhirpack/extraction/diagnosticreport.py
fhirpack/extraction/documentreference.py
fhirpack/extraction/encounter.py
fhirpack/extraction/endpoint.py
fhirpack/extraction/episodeofcare.py
fhirpack/extraction/familymemberhistory.py
fhirpack/extraction/imagingstudy.py
fhirpack/extraction/list.py
fhirpack/extraction/medicationadministration.py
fhirpack/extraction/medicationrequest.py
fhirpack/extraction/observation.py
fhirpack/extraction/patient.py
fhirpack/extraction/patient_test.py
fhirpack/extraction/sample.py
fhirpack/load/__init__.py
fhirpack/load/base.py
fhirpack/load/condition.py
fhirpack/load/observation.py
fhirpack/load/patient.py
fhirpack/transformation/__init__.py
fhirpack/transformation/base.py
fhirpack/transformation/base_test.py
fhirpack/transformation/condition.py
fhirpack/transformation/observation.py
fhirpack/transformation/patient.py
fhirpack-0.0.9b0.dist-info/LICENSE.txt
fhirpack-0.0.9b0.dist-info/METADATA
fhirpack-0.0.9b0.dist-info/WHEEL
fhirpack-0.0.9b0.dist-info/entry_points.txt
fhirpack-0.0.9b0.dist-info/top_level.txt
fhirpack-0.0.9b0.dist-info/RECORD
