Metadata-Version: 2.1
Name: fhirpack
Version: 0.0.9b0
Summary: FHIRPACK (FHIR Python Analysis Client and Kit) is a general purpose FHIR client that simplifies the access, analysis and representation of FHIR and EHR data using PANDAS, an ETL philosophy and a functional syntax.
Home-page: https://github.com/fhirpack/main
Author: Jayson Salazar Rodriguez
Author-email: mail@jdsalaro.com
Project-URL: Documentation, https://github.com/fhirpack/main
Project-URL: Source, https://github.com/fhirpack/main/src
Project-URL: Changelog, https://github.com/fhirpack/main
Project-URL: Tracker, https://gitlab.com/fhirpack/main/-/issues
Project-URL: Download, https://github.com/fhirpack/main
Project-URL: Twitter, https://twitter.com/jdsalaro
Platform: any
Classifier: Development Status :: 4 - Beta
Classifier: Programming Language :: Python :: 3
Classifier: License :: OSI Approved :: MIT License
Classifier: Operating System :: OS Independent
Classifier: Intended Audience :: Healthcare Industry
Classifier: Intended Audience :: Information Technology
Classifier: Intended Audience :: Science/Research
Classifier: Topic :: Education
Classifier: Topic :: Scientific/Engineering
Classifier: Topic :: Scientific/Engineering :: Information Analysis
Classifier: Topic :: Scientific/Engineering :: Medical Science Apps.
Classifier: Topic :: Scientific/Engineering :: Visualization
Classifier: Topic :: Text Processing :: Linguistic
Requires-Python: >=3.9.6
License-File: LICENSE.txt
Requires-Dist: pytest
Requires-Dist: fhirpy
Requires-Dist: requests
Requires-Dist: pandas
Requires-Dist: numpy
Requires-Dist: matplotlib
Requires-Dist: toml
Requires-Dist: fhir.resources
Requires-Dist: authlib
Requires-Dist: pyjwt
Requires-Dist: tqdm
Requires-Dist: python-dotenv[cli]
Requires-Dist: click
Requires-Dist: python-magic
Requires-Dist: dicomweb-client
Requires-Dist: markupsafe (==2.0.1)
Requires-Dist: typeguard
Provides-Extra: testing
Requires-Dist: setuptools ; extra == 'testing'
Requires-Dist: pytest ; extra == 'testing'
Requires-Dist: pytest-cov ; extra == 'testing'
